flask_more/__init__.py
flask_more/core.py
flask_more/openapi.py
flask_more/py.typed
flask_more/schemas.py
flask_more/utils.py
flask_more/validate.py
flask_more/wraps.py
flask_more/templates/__init__.py
flask_more/templates/redoc.html
flask_more/templates/swagger.html
flask_more-0.2.2.dist-info/METADATA
flask_more-0.2.2.dist-info/WHEEL
flask_more-0.2.2.dist-info/licenses/LICENSE
flask_more-0.2.2.dist-info/RECORD
