Metadata-Version: 2.1
Name: Flask-More
Version: 0.2.2
Summary: Modernized Flask API builder with schema validator and OpenAPI
Project-URL: Homepage, https://github.com/ischaojie/flask-more
Project-URL: Documentation, https://flask-more.chaojie.fun
Project-URL: Source, https://github.com/ischaojie/flask-more
Author-email: chaojie <hi@chaojie.fun>
License-Expression: MIT
License-File: LICENSE
Keywords: api,flask,openapi,plugin,validator
Classifier: Development Status :: 4 - Beta
Classifier: Framework :: Flask
Classifier: Intended Audience :: Developers
Classifier: License :: OSI Approved :: MIT License
Classifier: Natural Language :: English
Classifier: Operating System :: OS Independent
Classifier: Programming Language :: Python :: 3.8
Classifier: Programming Language :: Python :: 3.9
Classifier: Programming Language :: Python :: 3.10
Classifier: Programming Language :: Python :: 3.11
Classifier: Programming Language :: Python :: Implementation :: CPython
Classifier: Programming Language :: Python :: Implementation :: PyPy
Classifier: Topic :: Software Development :: Libraries :: Python Modules
Requires-Python: >=3.8
Requires-Dist: flask
Requires-Dist: pydantic[email]
